distribubot/__init__.py
distribubot/distribubot.py
distribubot/utils.py
distribubot/version.py
distribubot-0.4.1.dist-info/LICENSE
distribubot-0.4.1.dist-info/METADATA
distribubot-0.4.1.dist-info/WHEEL
distribubot-0.4.1.dist-info/entry_points.txt
distribubot-0.4.1.dist-info/top_level.txt
distribubot-0.4.1.dist-info/RECORD
