Metadata-Version: 2.1
Name: distribubot
Version: 0.4.1
Summary: Distribution of hive-engine Token through comments
Home-page: http://github.com/hive-engine/distribubot
Author: Holger Nahrstaedt
Author-email: holgernahrstaedt@gmx.de
Maintainer: Holger Nahrstaedt
Maintainer-email: holgernahrstaedt@gmx.de
License: UNKNOWN
Keywords: hive,token,hive-engine
Platform: UNKNOWN
Classifier: License :: OSI Approved :: MIT License
Classifier: Operating System :: OS Independent
Classifier: Programming Language :: Python
Classifier: Programming Language :: Python :: 2.7
Classifier: Programming Language :: Python :: 3
Classifier: Programming Language :: Python :: 3.4
Classifier: Programming Language :: Python :: 3.5
Classifier: Programming Language :: Python :: 3.6
Classifier: Development Status :: 4 - Beta
Classifier: Intended Audience :: Developers
Requires-Dist: beem
Requires-Dist: hiveengine
